prompt_library/__init__.py
prompt_library/cli.py
prompt_library/main.py
prompt_library/core/__init__.py
prompt_library/core/detector.py
prompt_library/core/key_descriptions.py
prompt_library/core/pipeline.py
prompt_library/core/redactor.py
prompt_library/data/context-library.json
prompt_library/data/patterns.json
prompt_library/data/pii-protection.json
prompt_library/data/redaction-rules.json
prompt_library/engines/__init__.py
prompt_library/engines/context/__init__.py
prompt_library/engines/context/context_engine.py
privacy_prompt_library-1.2.0.dist-info/METADATA
privacy_prompt_library-1.2.0.dist-info/WHEEL
privacy_prompt_library-1.2.0.dist-info/entry_points.txt
privacy_prompt_library-1.2.0.dist-info/licenses/LICENSE
privacy_prompt_library-1.2.0.dist-info/RECORD
