Metadata-Version: 2.4
Name: privacy-prompt-library
Version: 1.2.0
Summary: A privacy-preserving prompt transformation library with smart multiple key combinations that reduce redundancy by 50%+ while maintaining complete accessibility context.
Project-URL: Homepage, https://github.com/git-markkuria/kanuni-layer-sdk
Project-URL: Repository, https://github.com/git-markkuria/kanuni-layer-sdk.git
Project-URL: Documentation, https://github.com/git-markkuria/kanuni-layer-sdk#readme
Project-URL: Issues, https://github.com/git-markkuria/kanuni-layer-sdk/issues
Author-email: Accessibility Team <accessibility@example.com>
Maintainer-email: Sherry Kisilu <t-skisilu@microsoft.com>
License: MIT License
License-File: LICENSE
Keywords: accessibility,ai,disability,nlp,privacy,prompt,redaction,transformation
Classifier: Development Status :: 4 - Beta
Classifier: Intended Audience :: Developers
Classifier: Intended Audience :: Science/Research
Classifier: License :: OSI Approved :: MIT License
Classifier: Operating System :: OS Independent
Classifier: Programming Language :: Python :: 3
Classifier: Programming Language :: Python :: 3.8
Classifier: Programming Language :: Python :: 3.9
Classifier: Programming Language :: Python :: 3.10
Classifier: Programming Language :: Python :: 3.11
Classifier: Programming Language :: Python :: 3.12
Classifier: Topic :: Scientific/Engineering :: Artificial Intelligence
Classifier: Topic :: Software Development :: Libraries :: Python Modules
Classifier: Topic :: Text Processing :: Linguistic
Requires-Python: >=3.8
Requires-Dist: aiofiles>=23.0.0
Requires-Dist: pydantic>=2.0.0
Requires-Dist: typing-extensions>=4.0.0
Provides-Extra: dev
Requires-Dist: black>=23.0.0; extra == 'dev'
Requires-Dist: flake8>=6.0.0; extra == 'dev'
Requires-Dist: isort>=5.12.0; extra == 'dev'
Requires-Dist: mypy>=1.0.0; extra == 'dev'
Requires-Dist: pytest-asyncio>=0.21.0; extra == 'dev'
Requires-Dist: pytest>=7.0.0; extra == 'dev'
Provides-Extra: docs
Requires-Dist: sphinx-rtd-theme>=1.0.0; extra == 'docs'
Requires-Dist: sphinx>=6.0.0; extra == 'docs'
Provides-Extra: test
Requires-Dist: pytest-asyncio>=0.21.0; extra == 'test'
Requires-Dist: pytest-cov>=4.0.0; extra == 'test'
Requires-Dist: pytest>=7.0.0; extra == 'test'
